unstructured_document_viewer/__init__.py
unstructured_document_viewer/unstructured_document_viewer.py
unstructured_document_viewer-1.0.0.dist-info/LICENSE
unstructured_document_viewer-1.0.0.dist-info/METADATA
unstructured_document_viewer-1.0.0.dist-info/WHEEL
unstructured_document_viewer-1.0.0.dist-info/top_level.txt
unstructured_document_viewer-1.0.0.dist-info/RECORD
