Metadata-Version: 2.1
Name: unstructured-document-viewer
Version: 1.0.0
Summary: Unstructured Document Viewer
Home-page: https://github.com/preprocess-co/unstructured-document-viewer
Author: Preprocess Team
Author-email: support@preprocess.co
Keywords: unstructured,document,viewer,rag,pdf,preview
Classifier: Development Status :: 4 - Beta
Classifier: Intended Audience :: Developers
Classifier: License :: OSI Approved :: MIT License
Classifier: Programming Language :: Python :: 3
Classifier: Programming Language :: Python :: 3.8
Classifier: Programming Language :: Python :: 3.9
Classifier: Programming Language :: Python :: 3.10
Classifier: Programming Language :: Python :: 3.11
Requires-Python: >=3.8
License-File: LICENSE
Requires-Dist: rag-document-viewer >=1.0.0
